README.md
translator_testing_model/README.md
translator_testing_model/adaptor/test_case_generator.py
translator_testing_model/adaptor/testrunner.py
translator_testing_model/datamodel/README.md
translator_testing_model/datamodel/pydanticmodel.py
translator_testing_model/datamodel/pydanticmodel_v2.py
translator_testing_model/datamodel/translator_testing_model.py
translator_testing_model/schema/README.md
translator_testing_model/schema/translator_testing_model.yaml
translator_testing_model/scripts/GitHub_issue_parser.py
translator_testing_model/scripts/generate_suite_for_demo.py
translator_testing_model/scripts/test_suite_generator.py
translator_testing_model-2.3.0.dist-info/LICENSE
translator_testing_model-2.3.0.dist-info/METADATA
translator_testing_model-2.3.0.dist-info/WHEEL
translator_testing_model-2.3.0.dist-info/RECORD
