Metadata-Version: 2.1
Name: translator_testing_model
Version: 2.3.0
Summary: This is the project description.
License: MIT
Author: Sierra Moxon
Author-email: sierra.taylor@gmail.com
Requires-Python: >=3.9,<3.13
Classifier: License :: OSI Approved :: MIT License
Classifier: Programming Language :: Python :: 3
Classifier: Programming Language :: Python :: 3.9
Classifier: Programming Language :: Python :: 3.10
Classifier: Programming Language :: Python :: 3.11
Classifier: Programming Language :: Python :: 3.12
Provides-Extra: docs
Requires-Dist: bmt (>=1.2.1,<2.0.0)
Requires-Dist: linkml (>=1.6.1,<2.0.0) ; extra == "docs"
Requires-Dist: linkml-runtime (>=1.6.1,<2.0.0)
Requires-Dist: pandas (>=2.1.2,<3.0.0)
Requires-Dist: pydantic (>=1.10.13,<2.0.0)
